workit/__init__.py
workit-0.1.0.dist-info/WHEEL
workit-0.1.0.dist-info/METADATA
workit-0.1.0.dist-info/RECORD
